{
  "summary": {
    "total_value": 100184697,
    "daily_pnl": -2086304,
    "daily_return": -2.04,
    "total_pnl": 184697,
    "total_return": 0.18,
    "cash": -24841142,
    "cash_percent": -24.8,
    "unrealized_pnl": -4123545,
    "realized_pnl": 4308242
  },
  "history": [
    {
      "date": "2026-02-23",
      "value": 102095917
    },
    {
      "date": "2026-02-24",
      "value": 102325683
    },
    {
      "date": "2026-02-25",
      "value": 102342195
    },
    {
      "date": "2026-02-26",
      "value": 102271001
    },
    {
      "date": "2026-02-27",
      "value": 100184697
    }
  ],
  "holdings": [
    {
      "name": "한국앤컴퍼니",
      "symbol": "000240",
      "sector": "Automotive",
      "quantity": 201,
      "avg_price": 33397,
      "current_price": 31400,
      "value": 6311400,
      "pnl": -459564,
      "pnl_percent": -6.85,
      "account": "Account 8119599511"
    },
    {
      "name": "동아쏘시오홀딩스",
      "symbol": "000640",
      "sector": "Pharma",
      "quantity": 36,
      "avg_price": 119031,
      "current_price": 116500,
      "value": 4194000,
      "pnl": -129148,
      "pnl_percent": -3.01,
      "account": "Account 8119599511"
    },
    {
      "name": "한화",
      "symbol": "000880",
      "sector": "Conglomerate",
      "quantity": 6,
      "avg_price": 134658,
      "current_price": 138200,
      "value": 829200,
      "pnl": 13873,
      "pnl_percent": 1.72,
      "account": "Account 8119599511"
    },
    {
      "name": "DB하이텍",
      "symbol": "000990",
      "sector": "Semiconductors",
      "quantity": 43,
      "avg_price": 91325,
      "current_price": 95600,
      "value": 4110800,
      "pnl": 147470,
      "pnl_percent": 3.76,
      "account": "Account 8119599511"
    },
    {
      "name": "삼성전자",
      "symbol": "005930",
      "sector": "Electronics",
      "quantity": 10,
      "avg_price": 190641,
      "current_price": 215500,
      "value": 2155000,
      "pnl": 230068,
      "pnl_percent": 12.07,
      "account": "Account 8119599511"
    },
    {
      "name": "한국전력",
      "symbol": "015760",
      "sector": "Utilities",
      "quantity": 63,
      "avg_price": 61129,
      "current_price": 59400,
      "value": 3742200,
      "pnl": -142995,
      "pnl_percent": -3.71,
      "account": "Account 8119599511"
    },
    {
      "name": "SK가스",
      "symbol": "018670",
      "sector": "Utilities",
      "quantity": 33,
      "avg_price": 240856,
      "current_price": 234000,
      "value": 7722000,
      "pnl": -296524,
      "pnl_percent": -3.73,
      "account": "Account 8119599511"
    },
    {
      "name": "KT",
      "symbol": "030200",
      "sector": "Telecom",
      "quantity": 92,
      "avg_price": 65073,
      "current_price": 63700,
      "value": 5860400,
      "pnl": -179470,
      "pnl_percent": -3.0,
      "account": "Account 8119599511"
    },
    {
      "name": "한글과컴퓨터",
      "symbol": "030520",
      "sector": "Software",
      "quantity": 322,
      "avg_price": 23163,
      "current_price": 22600,
      "value": 7277200,
      "pnl": -247544,
      "pnl_percent": -3.32,
      "account": "Account 8119599511"
    },
    {
      "name": "LG유플러스",
      "symbol": "032640",
      "sector": "Telecom",
      "quantity": 222,
      "avg_price": 17261,
      "current_price": 17110,
      "value": 3798420,
      "pnl": -67711,
      "pnl_percent": -1.77,
      "account": "Account 8119599511"
    },
    {
      "name": "NAVER",
      "symbol": "035420",
      "sector": "Internet",
      "quantity": 15,
      "avg_price": 252650,
      "current_price": 258500,
      "value": 3877500,
      "pnl": 53166,
      "pnl_percent": 1.4,
      "account": "Account 8119599511"
    },
    {
      "name": "현대로템",
      "symbol": "064350",
      "sector": "Defense",
      "quantity": 3,
      "avg_price": 219650,
      "current_price": 225250,
      "value": 675750,
      "pnl": 10790,
      "pnl_percent": 1.64,
      "account": "Account 8119599511"
    },
    {
      "name": "SOOP",
      "symbol": "067160",
      "sector": "Internet",
      "quantity": 71,
      "avg_price": 70321,
      "current_price": 69800,
      "value": 4955800,
      "pnl": -81746,
      "pnl_percent": -1.64,
      "account": "Account 8119599511"
    },
    {
      "name": "한국금융지주",
      "symbol": "071050",
      "sector": "Finance",
      "quantity": 36,
      "avg_price": 275312,
      "current_price": 257500,
      "value": 9270000,
      "pnl": -726910,
      "pnl_percent": -7.33,
      "account": "Account 8119599511"
    },
    {
      "name": "미스토홀딩스",
      "symbol": "081660",
      "sector": "Holdings",
      "quantity": 177,
      "avg_price": 52033,
      "current_price": 50100,
      "value": 8867700,
      "pnl": -423113,
      "pnl_percent": -4.59,
      "account": "Account 8119599511"
    },
    {
      "name": "SNT에너지",
      "symbol": "100840",
      "sector": "Energy",
      "quantity": 205,
      "avg_price": 47473,
      "current_price": 45850,
      "value": 9399250,
      "pnl": -418483,
      "pnl_percent": -4.3,
      "account": "Account 8119599511"
    },
    {
      "name": "한국타이어앤테크놀로지",
      "symbol": "161390",
      "sector": "Automotive",
      "quantity": 69,
      "avg_price": 74157,
      "current_price": 72500,
      "value": 5002500,
      "pnl": -159750,
      "pnl_percent": -3.12,
      "account": "Account 8119599511"
    },
    {
      "name": "한국콜마",
      "symbol": "161890",
      "sector": "Cosmetics",
      "quantity": 54,
      "avg_price": 71953,
      "current_price": 76600,
      "value": 4136400,
      "pnl": 214616,
      "pnl_percent": 5.52,
      "account": "Account 8119599511"
    },
    {
      "name": "휴메딕스",
      "symbol": "200670",
      "sector": "Pharma",
      "quantity": 141,
      "avg_price": 44550,
      "current_price": 42950,
      "value": 6055950,
      "pnl": -280943,
      "pnl_percent": -4.47,
      "account": "Account 8119599511"
    },
    {
      "name": "넷마블",
      "symbol": "251270",
      "sector": "Games",
      "quantity": 174,
      "avg_price": 56497,
      "current_price": 53000,
      "value": 9222000,
      "pnl": -693664,
      "pnl_percent": -7.06,
      "account": "Account 8119599511"
    },
    {
      "name": "크래프톤",
      "symbol": "259960",
      "sector": "Games",
      "quantity": 20,
      "avg_price": 258212,
      "current_price": 247500,
      "value": 4950000,
      "pnl": -259525,
      "pnl_percent": -5.03,
      "account": "Account 8119599511"
    },
    {
      "name": "LX홀딩스",
      "symbol": "383800",
      "sector": "Conglomerate",
      "quantity": 474,
      "avg_price": 9554,
      "current_price": 9200,
      "value": 4360800,
      "pnl": -207577,
      "pnl_percent": -4.58,
      "account": "Account 8119599511"
    },
    {
      "name": "시프트업",
      "symbol": "462870",
      "sector": "Games",
      "quantity": 142,
      "avg_price": 33635,
      "current_price": 32800,
      "value": 4657600,
      "pnl": -160824,
      "pnl_percent": -3.37,
      "account": "Account 8119599511"
    },
    {
      "name": "삼양컴텍",
      "symbol": "484590",
      "sector": "Defense",
      "quantity": 254,
      "avg_price": 12396,
      "current_price": 13070,
      "value": 3319780,
      "pnl": 141985,
      "pnl_percent": 4.51,
      "account": "Account 8119599511"
    }
  ],
  "accounts": [
    {
      "name": "Account 8119599511",
      "total_value": 100184697,
      "cash": -24841142,
      "equity": 124751650
    }
  ],
  "virtual_accounts": [
    {
      "name": "삼성전자_1",
      "real_account_ref": "Account 8119599511",
      "allocation_ratio": 0.04000000000000001,
      "strategy_type": "LEADER",
      "rise_pct": 10.0,
      "dip_pct": 0,
      "total_value": 181400,
      "cash": 181400,
      "equity": 0,
      "unrealized_pnl": 0,
      "realized_pnl": -547848,
      "buy_count": 22,
      "sell_count": 3,
      "sector": "Electronics"
    },
    {
      "name": "삼성전자_2",
      "real_account_ref": "Account 8119599511",
      "allocation_ratio": 0.015,
      "strategy_type": "FOLLOWER",
      "rise_pct": 2.0,
      "dip_pct": 1.0,
      "total_value": 1500000,
      "cash": 1500000,
      "equity": 0,
      "unrealized_pnl": 0,
      "realized_pnl": 0,
      "buy_count": 0,
      "sell_count": 0,
      "sector": "Electronics"
    },
    {
      "name": "삼성전자_3",
      "real_account_ref": "Account 8119599511",
      "allocation_ratio": 0.015,
      "strategy_type": "FOLLOWER",
      "rise_pct": 3.0,
      "dip_pct": 2.0,
      "total_value": 1500000,
      "cash": 1500000,
      "equity": 0,
      "unrealized_pnl": 0,
      "realized_pnl": 0,
      "buy_count": 0,
      "sell_count": 0,
      "sector": "Electronics"
    },
    {
      "name": "삼성전자_4",
      "real_account_ref": "Account 8119599511",
      "allocation_ratio": 0.015,
      "strategy_type": "FOLLOWER",
      "rise_pct": 3.0,
      "dip_pct": 3.0,
      "total_value": 1500000,
      "cash": 1500000,
      "equity": 0,
      "unrealized_pnl": 0,
      "realized_pnl": 0,
      "buy_count": 0,
      "sell_count": 0,
      "sector": "Electronics"
    },
    {
      "name": "삼성전자_5",
      "real_account_ref": "Account 8119599511",
      "allocation_ratio": 0.015,
      "strategy_type": "FOLLOWER",
      "rise_pct": 3.0,
      "dip_pct": 4.0,
      "total_value": 1500000,
      "cash": 1500000,
      "equity": 0,
      "unrealized_pnl": 0,
      "realized_pnl": 0,
      "buy_count": 0,
      "sell_count": 0,
      "sector": "Electronics"
    },
    {
      "name": "LG유플러스_1",
      "real_account_ref": "Account 8119599511",
      "allocation_ratio": 0.04000000000000001,
      "strategy_type": "LEADER",
      "rise_pct": 10.0,
      "dip_pct": 0,
      "total_value": 3962055,
      "cash": 163635,
      "equity": 3798420,
      "unrealized_pnl": -37945,
      "realized_pnl": 0,
      "buy_count": 74,
      "sell_count": 0,
      "sector": "Telecom"
    },
    {
      "name": "LG유플러스_2",
      "real_account_ref": "Account 8119599511",
      "allocation_ratio": 0.015,
      "strategy_type": "FOLLOWER",
      "rise_pct": 3.0,
      "dip_pct": 1.0,
      "total_value": 1526800,
      "cash": 1526800,
      "equity": 0,
      "unrealized_pnl": 0,
      "realized_pnl": 26799,
      "buy_count": 18,
      "sell_count": 9,
      "sector": "Telecom"
    },
    {
      "name": "LG유플러스_3",
      "real_account_ref": "Account 8119599511",
      "allocation_ratio": 0.015,
      "strategy_type": "FOLLOWER",
      "rise_pct": 3.0,
      "dip_pct": 2.0,
      "total_value": 1504190,
      "cash": 1504190,
      "equity": 0,
      "unrealized_pnl": 0,
      "realized_pnl": 4190,
      "buy_count": 5,
      "sell_count": 2,
      "sector": "Telecom"
    },
    {
      "name": "LG유플러스_4",
      "real_account_ref": "Account 8119599511",
      "allocation_ratio": 0.015,
      "strategy_type": "FOLLOWER",
      "rise_pct": 3.0,
      "dip_pct": 3.0,
      "total_value": 1500000,
      "cash": 1500000,
      "equity": 0,
      "unrealized_pnl": 0,
      "realized_pnl": 0,
      "buy_count": 0,
      "sell_count": 0,
      "sector": "Telecom"
    },
    {
      "name": "LG유플러스_5",
      "real_account_ref": "Account 8119599511",
      "allocation_ratio": 0.015,
      "strategy_type": "FOLLOWER",
      "rise_pct": 3.0,
      "dip_pct": 4.0,
      "total_value": 1500000,
      "cash": 1500000,
      "equity": 0,
      "unrealized_pnl": 0,
      "realized_pnl": 0,
      "buy_count": 0,
      "sell_count": 0,
      "sector": "Telecom"
    },
    {
      "name": "크래프톤_1",
      "real_account_ref": "Account 8119599511",
      "allocation_ratio": 0.04000000000000001,
      "strategy_type": "LEADER",
      "rise_pct": 10.0,
      "dip_pct": 0,
      "total_value": 3825500,
      "cash": 113000,
      "equity": 3712500,
      "unrealized_pnl": -174500,
      "realized_pnl": 0,
      "buy_count": 15,
      "sell_count": 0,
      "sector": "Games"
    },
    {
      "name": "크래프톤_2",
      "real_account_ref": "Account 8119599511",
      "allocation_ratio": 0.015,
      "strategy_type": "FOLLOWER",
      "rise_pct": 3.0,
      "dip_pct": 1.0,
      "total_value": 1490000,
      "cash": 747500,
      "equity": 742500,
      "unrealized_pnl": -28000,
      "realized_pnl": 18000,
      "buy_count": 5,
      "sell_count": 1,
      "sector": "Games"
    },
    {
      "name": "크래프톤_3",
      "real_account_ref": "Account 8119599511",
      "allocation_ratio": 0.015,
      "strategy_type": "FOLLOWER",
      "rise_pct": 3.0,
      "dip_pct": 2.0,
      "total_value": 1484500,
      "cash": 989500,
      "equity": 495000,
      "unrealized_pnl": -15500,
      "realized_pnl": 0,
      "buy_count": 2,
      "sell_count": 0,
      "sector": "Games"
    },
    {
      "name": "크래프톤_4",
      "real_account_ref": "Account 8119599511",
      "allocation_ratio": 0.015,
      "strategy_type": "FOLLOWER",
      "rise_pct": 3.0,
      "dip_pct": 3.0,
      "total_value": 1500000,
      "cash": 1500000,
      "equity": 0,
      "unrealized_pnl": 0,
      "realized_pnl": 0,
      "buy_count": 0,
      "sell_count": 0,
      "sector": "Games"
    },
    {
      "name": "크래프톤_5",
      "real_account_ref": "Account 8119599511",
      "allocation_ratio": 0.015,
      "strategy_type": "FOLLOWER",
      "rise_pct": 3.0,
      "dip_pct": 4.0,
      "total_value": 1500000,
      "cash": 1500000,
      "equity": 0,
      "unrealized_pnl": 0,
      "realized_pnl": 0,
      "buy_count": 0,
      "sell_count": 0,
      "sector": "Games"
    },
    {
      "name": "KT_1",
      "real_account_ref": "Account 8119599511",
      "allocation_ratio": 0.04000000000000001,
      "strategy_type": "LEADER",
      "rise_pct": 10.0,
      "dip_pct": 0,
      "total_value": 3908050,
      "cash": 22350,
      "equity": 3885700,
      "unrealized_pnl": -91950,
      "realized_pnl": 0,
      "buy_count": 61,
      "sell_count": 0,
      "sector": "Telecom"
    },
    {
      "name": "KT_2",
      "real_account_ref": "Account 8119599511",
      "allocation_ratio": 0.015,
      "strategy_type": "FOLLOWER",
      "rise_pct": 3.0,
      "dip_pct": 1.0,
      "total_value": 1483950,
      "cash": 337350,
      "equity": 1146600,
      "unrealized_pnl": -20050,
      "realized_pnl": 4000,
      "buy_count": 17,
      "sell_count": 1,
      "sector": "Telecom"
    },
    {
      "name": "KT_3",
      "real_account_ref": "Account 8119599511",
      "allocation_ratio": 0.015,
      "strategy_type": "FOLLOWER",
      "rise_pct": 3.0,
      "dip_pct": 2.0,
      "total_value": 1491250,
      "cash": 1045350,
      "equity": 445900,
      "unrealized_pnl": -8750,
      "realized_pnl": 0,
      "buy_count": 6,
      "sell_count": 0,
      "sector": "Telecom"
    },
    {
      "name": "KT_4",
      "real_account_ref": "Account 8119599511",
      "allocation_ratio": 0.015,
      "strategy_type": "FOLLOWER",
      "rise_pct": 3.0,
      "dip_pct": 3.0,
      "total_value": 1494000,
      "cash": 1111800,
      "equity": 382200,
      "unrealized_pnl": -6000,
      "realized_pnl": 0,
      "buy_count": 4,
      "sell_count": 0,
      "sector": "Telecom"
    },
    {
      "name": "KT_5",
      "real_account_ref": "Account 8119599511",
      "allocation_ratio": 0.015,
      "strategy_type": "FOLLOWER",
      "rise_pct": 3.0,
      "dip_pct": 4.0,
      "total_value": 1497200,
      "cash": 1242400,
      "equity": 254800,
      "unrealized_pnl": -2800,
      "realized_pnl": 0,
      "buy_count": 4,
      "sell_count": 0,
      "sector": "Telecom"
    },
    {
      "name": "한국전력_1",
      "real_account_ref": "Account 8119599511",
      "allocation_ratio": 0.04000000000000001,
      "strategy_type": "LEADER",
      "rise_pct": 10.0,
      "dip_pct": 0,
      "total_value": 3885650,
      "cash": 143450,
      "equity": 3742200,
      "unrealized_pnl": -114350,
      "realized_pnl": 0,
      "buy_count": 63,
      "sell_count": 0,
      "sector": "Utilities"
    },
    {
      "name": "한국전력_2",
      "real_account_ref": "Account 8119599511",
      "allocation_ratio": 0.015,
      "strategy_type": "FOLLOWER",
      "rise_pct": 3.0,
      "dip_pct": 1.0,
      "total_value": 1520900,
      "cash": 1520900,
      "equity": 0,
      "unrealized_pnl": 0,
      "realized_pnl": 20899,
      "buy_count": 7,
      "sell_count": 1,
      "sector": "Utilities"
    },
    {
      "name": "한국전력_3",
      "real_account_ref": "Account 8119599511",
      "allocation_ratio": 0.015,
      "strategy_type": "FOLLOWER",
      "rise_pct": 3.0,
      "dip_pct": 2.0,
      "total_value": 1502800,
      "cash": 1146400,
      "equity": 356400,
      "unrealized_pnl": -3600,
      "realized_pnl": 6400,
      "buy_count": 6,
      "sell_count": 1,
      "sector": "Utilities"
    },
    {
      "name": "한국전력_4",
      "real_account_ref": "Account 8119599511",
      "allocation_ratio": 0.015,
      "strategy_type": "FOLLOWER",
      "rise_pct": 3.0,
      "dip_pct": 3.0,
      "total_value": 1499750,
      "cash": 1440350,
      "equity": 59400,
      "unrealized_pnl": -250,
      "realized_pnl": 0,
      "buy_count": 1,
      "sell_count": 0,
      "sector": "Utilities"
    },
    {
      "name": "한국전력_5",
      "real_account_ref": "Account 8119599511",
      "allocation_ratio": 0.015,
      "strategy_type": "FOLLOWER",
      "rise_pct": 3.0,
      "dip_pct": 4.0,
      "total_value": 1500000,
      "cash": 1500000,
      "equity": 0,
      "unrealized_pnl": 0,
      "realized_pnl": 0,
      "buy_count": 0,
      "sell_count": 0,
      "sector": "Utilities"
    },
    {
      "name": "SKHynix_1",
      "real_account_ref": "Account 8119599511",
      "allocation_ratio": 0.04000000000000001,
      "strategy_type": "LEADER",
      "rise_pct": 10.0,
      "dip_pct": 0,
      "total_value": 4356000,
      "cash": 4356000,
      "equity": 0,
      "unrealized_pnl": 0,
      "realized_pnl": 356000,
      "buy_count": 4,
      "sell_count": 1,
      "sector": "Electronics"
    },
    {
      "name": "SKHynix_2",
      "real_account_ref": "Account 8119599511",
      "allocation_ratio": 0.015,
      "strategy_type": "FOLLOWER",
      "rise_pct": 3.0,
      "dip_pct": 1.0,
      "total_value": 1540000,
      "cash": 1540000,
      "equity": 0,
      "unrealized_pnl": 0,
      "realized_pnl": 40000,
      "buy_count": 1,
      "sell_count": 1,
      "sector": "Electronics"
    },
    {
      "name": "SKHynix_3",
      "real_account_ref": "Account 8119599511",
      "allocation_ratio": 0.015,
      "strategy_type": "FOLLOWER",
      "rise_pct": 3.0,
      "dip_pct": 2.0,
      "total_value": 1500000,
      "cash": 1500000,
      "equity": 0,
      "unrealized_pnl": 0,
      "realized_pnl": 0,
      "buy_count": 0,
      "sell_count": 0,
      "sector": "Electronics"
    },
    {
      "name": "SKHynix_4",
      "real_account_ref": "Account 8119599511",
      "allocation_ratio": 0.015,
      "strategy_type": "FOLLOWER",
      "rise_pct": 3.0,
      "dip_pct": 3.0,
      "total_value": 1500000,
      "cash": 1500000,
      "equity": 0,
      "unrealized_pnl": 0,
      "realized_pnl": 0,
      "buy_count": 0,
      "sell_count": 0,
      "sector": "Electronics"
    },
    {
      "name": "SKHynix_5",
      "real_account_ref": "Account 8119599511",
      "allocation_ratio": 0.015,
      "strategy_type": "FOLLOWER",
      "rise_pct": 3.0,
      "dip_pct": 4.0,
      "total_value": 1500000,
      "cash": 1500000,
      "equity": 0,
      "unrealized_pnl": 0,
      "realized_pnl": 0,
      "buy_count": 0,
      "sell_count": 0,
      "sector": "Electronics"
    },
    {
      "name": "HyundaiGlovis_1",
      "real_account_ref": "Account 8119599511",
      "allocation_ratio": 0.04000000000000001,
      "strategy_type": "LEADER",
      "rise_pct": 10.0,
      "dip_pct": 0,
      "total_value": 4402500,
      "cash": 4402500,
      "equity": 0,
      "unrealized_pnl": 0,
      "realized_pnl": 402500,
      "buy_count": 15,
      "sell_count": 1,
      "sector": "Logistics"
    },
    {
      "name": "HyundaiGlovis_2",
      "real_account_ref": "Account 8119599511",
      "allocation_ratio": 0.015,
      "strategy_type": "FOLLOWER",
      "rise_pct": 3.0,
      "dip_pct": 1.0,
      "total_value": 1529000,
      "cash": 1529000,
      "equity": 0,
      "unrealized_pnl": 0,
      "realized_pnl": 28999,
      "buy_count": 3,
      "sell_count": 1,
      "sector": "Logistics"
    },
    {
      "name": "HyundaiGlovis_3",
      "real_account_ref": "Account 8119599511",
      "allocation_ratio": 0.015,
      "strategy_type": "FOLLOWER",
      "rise_pct": 3.0,
      "dip_pct": 2.0,
      "total_value": 1516000,
      "cash": 1516000,
      "equity": 0,
      "unrealized_pnl": 0,
      "realized_pnl": 16000,
      "buy_count": 2,
      "sell_count": 1,
      "sector": "Logistics"
    },
    {
      "name": "HyundaiGlovis_4",
      "real_account_ref": "Account 8119599511",
      "allocation_ratio": 0.015,
      "strategy_type": "FOLLOWER",
      "rise_pct": 3.0,
      "dip_pct": 3.0,
      "total_value": 1500000,
      "cash": 1500000,
      "equity": 0,
      "unrealized_pnl": 0,
      "realized_pnl": 0,
      "buy_count": 0,
      "sell_count": 0,
      "sector": "Logistics"
    },
    {
      "name": "HyundaiGlovis_5",
      "real_account_ref": "Account 8119599511",
      "allocation_ratio": 0.015,
      "strategy_type": "FOLLOWER",
      "rise_pct": 3.0,
      "dip_pct": 4.0,
      "total_value": 1500000,
      "cash": 1500000,
      "equity": 0,
      "unrealized_pnl": 0,
      "realized_pnl": 0,
      "buy_count": 0,
      "sell_count": 0,
      "sector": "Logistics"
    },
    {
      "name": "현대로템_1",
      "real_account_ref": "Account 8119599511",
      "allocation_ratio": 0.04000000000000001,
      "strategy_type": "LEADER",
      "rise_pct": 10.0,
      "dip_pct": 0,
      "total_value": 4420250,
      "cash": 3744500,
      "equity": 675750,
      "unrealized_pnl": 15750,
      "realized_pnl": 404500,
      "buy_count": 22,
      "sell_count": 1,
      "sector": "Defense"
    },
    {
      "name": "현대로템_2",
      "real_account_ref": "Account 8119599511",
      "allocation_ratio": 0.015,
      "strategy_type": "FOLLOWER",
      "rise_pct": 3.0,
      "dip_pct": 1.0,
      "total_value": 1515000,
      "cash": 1515000,
      "equity": 0,
      "unrealized_pnl": 0,
      "realized_pnl": 15000,
      "buy_count": 2,
      "sell_count": 2,
      "sector": "Defense"
    },
    {
      "name": "현대로템_3",
      "real_account_ref": "Account 8119599511",
      "allocation_ratio": 0.015,
      "strategy_type": "FOLLOWER",
      "rise_pct": 3.0,
      "dip_pct": 2.0,
      "total_value": 1507000,
      "cash": 1507000,
      "equity": 0,
      "unrealized_pnl": 0,
      "realized_pnl": 7000,
      "buy_count": 1,
      "sell_count": 1,
      "sector": "Defense"
    },
    {
      "name": "현대로템_4",
      "real_account_ref": "Account 8119599511",
      "allocation_ratio": 0.015,
      "strategy_type": "FOLLOWER",
      "rise_pct": 3.0,
      "dip_pct": 3.0,
      "total_value": 1500000,
      "cash": 1500000,
      "equity": 0,
      "unrealized_pnl": 0,
      "realized_pnl": 0,
      "buy_count": 0,
      "sell_count": 0,
      "sector": "Defense"
    },
    {
      "name": "현대로템_5",
      "real_account_ref": "Account 8119599511",
      "allocation_ratio": 0.015,
      "strategy_type": "FOLLOWER",
      "rise_pct": 3.0,
      "dip_pct": 4.0,
      "total_value": 1500000,
      "cash": 1500000,
      "equity": 0,
      "unrealized_pnl": 0,
      "realized_pnl": 0,
      "buy_count": 0,
      "sell_count": 0,
      "sector": "Defense"
    },
    {
      "name": "한국금융지주_1",
      "real_account_ref": "Account 8119599511",
      "allocation_ratio": 0.04000000000000001,
      "strategy_type": "LEADER",
      "rise_pct": 10.0,
      "dip_pct": 0,
      "total_value": 4178750,
      "cash": 58750,
      "equity": 4120000,
      "unrealized_pnl": -468750,
      "realized_pnl": 647500,
      "buy_count": 32,
      "sell_count": 1,
      "sector": "Finance"
    },
    {
      "name": "한국금융지주_2",
      "real_account_ref": "Account 8119599511",
      "allocation_ratio": 0.015,
      "strategy_type": "FOLLOWER",
      "rise_pct": 3.0,
      "dip_pct": 1.0,
      "total_value": 1459000,
      "cash": 171500,
      "equity": 1287500,
      "unrealized_pnl": -41000,
      "realized_pnl": 0,
      "buy_count": 5,
      "sell_count": 0,
      "sector": "Finance"
    },
    {
      "name": "한국금융지주_3",
      "real_account_ref": "Account 8119599511",
      "allocation_ratio": 0.015,
      "strategy_type": "FOLLOWER",
      "rise_pct": 3.0,
      "dip_pct": 2.0,
      "total_value": 1459500,
      "cash": 172000,
      "equity": 1287500,
      "unrealized_pnl": -40500,
      "realized_pnl": 0,
      "buy_count": 5,
      "sell_count": 0,
      "sector": "Finance"
    },
    {
      "name": "한국금융지주_4",
      "real_account_ref": "Account 8119599511",
      "allocation_ratio": 0.015,
      "strategy_type": "FOLLOWER",
      "rise_pct": 3.0,
      "dip_pct": 3.0,
      "total_value": 1450500,
      "cash": 163000,
      "equity": 1287500,
      "unrealized_pnl": -49500,
      "realized_pnl": 0,
      "buy_count": 5,
      "sell_count": 0,
      "sector": "Finance"
    },
    {
      "name": "한국금융지주_5",
      "real_account_ref": "Account 8119599511",
      "allocation_ratio": 0.015,
      "strategy_type": "FOLLOWER",
      "rise_pct": 3.0,
      "dip_pct": 4.0,
      "total_value": 1460000,
      "cash": 172500,
      "equity": 1287500,
      "unrealized_pnl": -40000,
      "realized_pnl": 0,
      "buy_count": 5,
      "sell_count": 0,
      "sector": "Finance"
    },
    {
      "name": "넷마블_1",
      "real_account_ref": "Account 8119599511",
      "allocation_ratio": 0.04000000000000001,
      "strategy_type": "LEADER",
      "rise_pct": 10.0,
      "dip_pct": 0,
      "total_value": 3705600,
      "cash": 101600,
      "equity": 3604000,
      "unrealized_pnl": -294400,
      "realized_pnl": 0,
      "buy_count": 62,
      "sell_count": 0,
      "sector": "Games"
    },
    {
      "name": "넷마블_2",
      "real_account_ref": "Account 8119599511",
      "allocation_ratio": 0.015,
      "strategy_type": "FOLLOWER",
      "rise_pct": 3.0,
      "dip_pct": 1.0,
      "total_value": 1400100,
      "cash": 22100,
      "equity": 1378000,
      "unrealized_pnl": -99900,
      "realized_pnl": 0,
      "buy_count": 20,
      "sell_count": 0,
      "sector": "Games"
    },
    {
      "name": "넷마블_3",
      "real_account_ref": "Account 8119599511",
      "allocation_ratio": 0.015,
      "strategy_type": "FOLLOWER",
      "rise_pct": 3.0,
      "dip_pct": 2.0,
      "total_value": 1418400,
      "cash": 40400,
      "equity": 1378000,
      "unrealized_pnl": -81600,
      "realized_pnl": 0,
      "buy_count": 20,
      "sell_count": 0,
      "sector": "Games"
    },
    {
      "name": "넷마블_4",
      "real_account_ref": "Account 8119599511",
      "allocation_ratio": 0.015,
      "strategy_type": "FOLLOWER",
      "rise_pct": 3.0,
      "dip_pct": 3.0,
      "total_value": 1431000,
      "cash": 0,
      "equity": 1431000,
      "unrealized_pnl": -69000,
      "realized_pnl": 0,
      "buy_count": 23,
      "sell_count": 0,
      "sector": "Games"
    },
    {
      "name": "넷마블_5",
      "real_account_ref": "Account 8119599511",
      "allocation_ratio": 0.015,
      "strategy_type": "FOLLOWER",
      "rise_pct": 3.0,
      "dip_pct": 4.0,
      "total_value": 1439300,
      "cash": 8300,
      "equity": 1431000,
      "unrealized_pnl": -60700,
      "realized_pnl": 0,
      "buy_count": 20,
      "sell_count": 0,
      "sector": "Games"
    },
    {
      "name": "한국타이어앤테크놀로지_1",
      "real_account_ref": "Account 8119599511",
      "allocation_ratio": 0.04000000000000001,
      "strategy_type": "LEADER",
      "rise_pct": 10.0,
      "dip_pct": 0,
      "total_value": 3916500,
      "cash": 1500,
      "equity": 3915000,
      "unrealized_pnl": -83500,
      "realized_pnl": 0,
      "buy_count": 41,
      "sell_count": 0,
      "sector": "Automotive"
    },
    {
      "name": "한국타이어앤테크놀로지_2",
      "real_account_ref": "Account 8119599511",
      "allocation_ratio": 0.015,
      "strategy_type": "FOLLOWER",
      "rise_pct": 3.0,
      "dip_pct": 1.0,
      "total_value": 1488350,
      "cash": 908350,
      "equity": 580000,
      "unrealized_pnl": -17994.444444444496,
      "realized_pnl": 6344,
      "buy_count": 11,
      "sell_count": 3,
      "sector": "Automotive"
    },
    {
      "name": "한국타이어앤테크놀로지_3",
      "real_account_ref": "Account 8119599511",
      "allocation_ratio": 0.015,
      "strategy_type": "FOLLOWER",
      "rise_pct": 3.0,
      "dip_pct": 2.0,
      "total_value": 1495250,
      "cash": 1060250,
      "equity": 435000,
      "unrealized_pnl": -10012.5,
      "realized_pnl": 5262,
      "buy_count": 8,
      "sell_count": 2,
      "sector": "Automotive"
    },
    {
      "name": "한국타이어앤테크놀로지_4",
      "real_account_ref": "Account 8119599511",
      "allocation_ratio": 0.015,
      "strategy_type": "FOLLOWER",
      "rise_pct": 3.0,
      "dip_pct": 3.0,
      "total_value": 1498500,
      "cash": 1426000,
      "equity": 72500,
      "unrealized_pnl": -1500,
      "realized_pnl": 0,
      "buy_count": 1,
      "sell_count": 0,
      "sector": "Automotive"
    },
    {
      "name": "한국타이어앤테크놀로지_5",
      "real_account_ref": "Account 8119599511",
      "allocation_ratio": 0.015,
      "strategy_type": "FOLLOWER",
      "rise_pct": 3.0,
      "dip_pct": 4.0,
      "total_value": 1500000,
      "cash": 1500000,
      "equity": 0,
      "unrealized_pnl": 0,
      "realized_pnl": 0,
      "buy_count": 0,
      "sell_count": 0,
      "sector": "Automotive"
    },
    {
      "name": "한국콜마_1",
      "real_account_ref": "Account 8119599511",
      "allocation_ratio": 0.04000000000000001,
      "strategy_type": "LEADER",
      "rise_pct": 10.0,
      "dip_pct": 0,
      "total_value": 4205300,
      "cash": 68900,
      "equity": 4136400,
      "unrealized_pnl": 205300,
      "realized_pnl": 0,
      "buy_count": 41,
      "sell_count": 0,
      "sector": "Cosmetics"
    },
    {
      "name": "한국콜마_2",
      "real_account_ref": "Account 8119599511",
      "allocation_ratio": 0.015,
      "strategy_type": "FOLLOWER",
      "rise_pct": 3.0,
      "dip_pct": 1.0,
      "total_value": 1566400,
      "cash": 1566400,
      "equity": 0,
      "unrealized_pnl": 0,
      "realized_pnl": 66400,
      "buy_count": 20,
      "sell_count": 1,
      "sector": "Cosmetics"
    },
    {
      "name": "한국콜마_3",
      "real_account_ref": "Account 8119599511",
      "allocation_ratio": 0.015,
      "strategy_type": "FOLLOWER",
      "rise_pct": 3.0,
      "dip_pct": 2.0,
      "total_value": 1596950,
      "cash": 1596950,
      "equity": 0,
      "unrealized_pnl": 0,
      "realized_pnl": 96950,
      "buy_count": 21,
      "sell_count": 1,
      "sector": "Cosmetics"
    },
    {
      "name": "한국콜마_4",
      "real_account_ref": "Account 8119599511",
      "allocation_ratio": 0.015,
      "strategy_type": "FOLLOWER",
      "rise_pct": 3.0,
      "dip_pct": 3.0,
      "total_value": 1603100,
      "cash": 1603100,
      "equity": 0,
      "unrealized_pnl": 0,
      "realized_pnl": 103099,
      "buy_count": 19,
      "sell_count": 4,
      "sector": "Cosmetics"
    },
    {
      "name": "한국콜마_5",
      "real_account_ref": "Account 8119599511",
      "allocation_ratio": 0.015,
      "strategy_type": "FOLLOWER",
      "rise_pct": 3.0,
      "dip_pct": 4.0,
      "total_value": 1534400,
      "cash": 1534400,
      "equity": 0,
      "unrealized_pnl": 0,
      "realized_pnl": 34400,
      "buy_count": 8,
      "sell_count": 1,
      "sector": "Cosmetics"
    },
    {
      "name": "SNT에너지_1",
      "real_account_ref": "Account 8119599511",
      "allocation_ratio": 0.04000000000000001,
      "strategy_type": "LEADER",
      "rise_pct": 10.0,
      "dip_pct": 0,
      "total_value": 3817350,
      "cash": 103500,
      "equity": 3713850,
      "unrealized_pnl": -182650,
      "realized_pnl": 0,
      "buy_count": 43,
      "sell_count": 0,
      "sector": "Energy"
    },
    {
      "name": "SNT에너지_2",
      "real_account_ref": "Account 8119599511",
      "allocation_ratio": 0.015,
      "strategy_type": "FOLLOWER",
      "rise_pct": 3.0,
      "dip_pct": 1.0,
      "total_value": 1461350,
      "cash": 40000,
      "equity": 1421350,
      "unrealized_pnl": -40150,
      "realized_pnl": 1500,
      "buy_count": 24,
      "sell_count": 1,
      "sector": "Energy"
    },
    {
      "name": "SNT에너지_3",
      "real_account_ref": "Account 8119599511",
      "allocation_ratio": 0.015,
      "strategy_type": "FOLLOWER",
      "rise_pct": 3.0,
      "dip_pct": 2.0,
      "total_value": 1461350,
      "cash": 40000,
      "equity": 1421350,
      "unrealized_pnl": -40250,
      "realized_pnl": 1600,
      "buy_count": 23,
      "sell_count": 1,
      "sector": "Energy"
    },
    {
      "name": "SNT에너지_4",
      "real_account_ref": "Account 8119599511",
      "allocation_ratio": 0.015,
      "strategy_type": "FOLLOWER",
      "rise_pct": 3.0,
      "dip_pct": 3.0,
      "total_value": 1459900,
      "cash": 38550,
      "equity": 1421350,
      "unrealized_pnl": -40100,
      "realized_pnl": 0,
      "buy_count": 21,
      "sell_count": 0,
      "sector": "Energy"
    },
    {
      "name": "SNT에너지_5",
      "real_account_ref": "Account 8119599511",
      "allocation_ratio": 0.015,
      "strategy_type": "FOLLOWER",
      "rise_pct": 3.0,
      "dip_pct": 4.0,
      "total_value": 1467500,
      "cash": 46150,
      "equity": 1421350,
      "unrealized_pnl": -32500,
      "realized_pnl": 0,
      "buy_count": 19,
      "sell_count": 0,
      "sector": "Energy"
    },
    {
      "name": "DB하이텍_1",
      "real_account_ref": "Account 8119599511",
      "allocation_ratio": 0.04000000000000001,
      "strategy_type": "LEADER",
      "rise_pct": 10.0,
      "dip_pct": 0,
      "total_value": 4146800,
      "cash": 36000,
      "equity": 4110800,
      "unrealized_pnl": 146800,
      "realized_pnl": 0,
      "buy_count": 39,
      "sell_count": 0,
      "sector": "Semiconductors"
    },
    {
      "name": "DB하이텍_2",
      "real_account_ref": "Account 8119599511",
      "allocation_ratio": 0.015,
      "strategy_type": "FOLLOWER",
      "rise_pct": 3.0,
      "dip_pct": 1.0,
      "total_value": 1545000,
      "cash": 1545000,
      "equity": 0,
      "unrealized_pnl": 0,
      "realized_pnl": 45000,
      "buy_count": 16,
      "sell_count": 1,
      "sector": "Semiconductors"
    },
    {
      "name": "DB하이텍_3",
      "real_account_ref": "Account 8119599511",
      "allocation_ratio": 0.015,
      "strategy_type": "FOLLOWER",
      "rise_pct": 3.0,
      "dip_pct": 2.0,
      "total_value": 1566400,
      "cash": 1566400,
      "equity": 0,
      "unrealized_pnl": 0,
      "realized_pnl": 66400,
      "buy_count": 21,
      "sell_count": 4,
      "sector": "Semiconductors"
    },
    {
      "name": "DB하이텍_4",
      "real_account_ref": "Account 8119599511",
      "allocation_ratio": 0.015,
      "strategy_type": "FOLLOWER",
      "rise_pct": 3.0,
      "dip_pct": 3.0,
      "total_value": 1573500,
      "cash": 1573500,
      "equity": 0,
      "unrealized_pnl": 0,
      "realized_pnl": 73500,
      "buy_count": 20,
      "sell_count": 6,
      "sector": "Semiconductors"
    },
    {
      "name": "DB하이텍_5",
      "real_account_ref": "Account 8119599511",
      "allocation_ratio": 0.015,
      "strategy_type": "FOLLOWER",
      "rise_pct": 3.0,
      "dip_pct": 4.0,
      "total_value": 1516300,
      "cash": 1516300,
      "equity": 0,
      "unrealized_pnl": 0,
      "realized_pnl": 16300,
      "buy_count": 6,
      "sell_count": 3,
      "sector": "Semiconductors"
    },
    {
      "name": "DaehanShipbuilding_1",
      "real_account_ref": "Account 8119599511",
      "allocation_ratio": 0.04000000000000001,
      "strategy_type": "LEADER",
      "rise_pct": 10.0,
      "dip_pct": 0,
      "total_value": 1596600,
      "cash": 1596600,
      "equity": 0,
      "unrealized_pnl": 0,
      "realized_pnl": 854199,
      "buy_count": 48,
      "sell_count": 2,
      "sector": "Shipbuilding"
    },
    {
      "name": "DaehanShipbuilding_2",
      "real_account_ref": "Account 8119599511",
      "allocation_ratio": 0.015,
      "strategy_type": "FOLLOWER",
      "rise_pct": 3.0,
      "dip_pct": 1.0,
      "total_value": 1524000,
      "cash": 1524000,
      "equity": 0,
      "unrealized_pnl": 0,
      "realized_pnl": 23999,
      "buy_count": 7,
      "sell_count": 7,
      "sector": "Shipbuilding"
    },
    {
      "name": "DaehanShipbuilding_3",
      "real_account_ref": "Account 8119599511",
      "allocation_ratio": 0.015,
      "strategy_type": "FOLLOWER",
      "rise_pct": 3.0,
      "dip_pct": 2.0,
      "total_value": 1515200,
      "cash": 1515200,
      "equity": 0,
      "unrealized_pnl": 0,
      "realized_pnl": 15200,
      "buy_count": 5,
      "sell_count": 5,
      "sector": "Shipbuilding"
    },
    {
      "name": "DaehanShipbuilding_4",
      "real_account_ref": "Account 8119599511",
      "allocation_ratio": 0.015,
      "strategy_type": "FOLLOWER",
      "rise_pct": 3.0,
      "dip_pct": 3.0,
      "total_value": 1511400,
      "cash": 1511400,
      "equity": 0,
      "unrealized_pnl": 0,
      "realized_pnl": 11400,
      "buy_count": 4,
      "sell_count": 4,
      "sector": "Shipbuilding"
    },
    {
      "name": "DaehanShipbuilding_5",
      "real_account_ref": "Account 8119599511",
      "allocation_ratio": 0.015,
      "strategy_type": "FOLLOWER",
      "rise_pct": 3.0,
      "dip_pct": 4.0,
      "total_value": 1509700,
      "cash": 1509700,
      "equity": 0,
      "unrealized_pnl": 0,
      "realized_pnl": 9700,
      "buy_count": 3,
      "sell_count": 3,
      "sector": "Shipbuilding"
    },
    {
      "name": "한화_1",
      "real_account_ref": "Account 8119599511",
      "allocation_ratio": 0.04000000000000001,
      "strategy_type": "LEADER",
      "rise_pct": 10.0,
      "dip_pct": 0,
      "total_value": 4426400,
      "cash": 3597200,
      "equity": 829200,
      "unrealized_pnl": 24800,
      "realized_pnl": 401600,
      "buy_count": 39,
      "sell_count": 1,
      "sector": "Conglomerate"
    },
    {
      "name": "한화_2",
      "real_account_ref": "Account 8119599511",
      "allocation_ratio": 0.015,
      "strategy_type": "FOLLOWER",
      "rise_pct": 3.0,
      "dip_pct": 1.0,
      "total_value": 1513300,
      "cash": 1513300,
      "equity": 0,
      "unrealized_pnl": 0,
      "realized_pnl": 13300,
      "buy_count": 3,
      "sell_count": 3,
      "sector": "Conglomerate"
    },
    {
      "name": "한화_3",
      "real_account_ref": "Account 8119599511",
      "allocation_ratio": 0.015,
      "strategy_type": "FOLLOWER",
      "rise_pct": 3.0,
      "dip_pct": 2.0,
      "total_value": 1504300,
      "cash": 1504300,
      "equity": 0,
      "unrealized_pnl": 0,
      "realized_pnl": 4300,
      "buy_count": 1,
      "sell_count": 1,
      "sector": "Conglomerate"
    },
    {
      "name": "한화_4",
      "real_account_ref": "Account 8119599511",
      "allocation_ratio": 0.015,
      "strategy_type": "FOLLOWER",
      "rise_pct": 3.0,
      "dip_pct": 3.0,
      "total_value": 1504500,
      "cash": 1504500,
      "equity": 0,
      "unrealized_pnl": 0,
      "realized_pnl": 4500,
      "buy_count": 1,
      "sell_count": 1,
      "sector": "Conglomerate"
    },
    {
      "name": "한화_5",
      "real_account_ref": "Account 8119599511",
      "allocation_ratio": 0.015,
      "strategy_type": "FOLLOWER",
      "rise_pct": 3.0,
      "dip_pct": 4.0,
      "total_value": 1504300,
      "cash": 1504300,
      "equity": 0,
      "unrealized_pnl": 0,
      "realized_pnl": 4300,
      "buy_count": 1,
      "sell_count": 1,
      "sector": "Conglomerate"
    },
    {
      "name": "NAVER_1",
      "real_account_ref": "Account 8119599511",
      "allocation_ratio": 0.04000000000000001,
      "strategy_type": "LEADER",
      "rise_pct": 10.0,
      "dip_pct": 0,
      "total_value": 4089000,
      "cash": 211500,
      "equity": 3877500,
      "unrealized_pnl": 89000,
      "realized_pnl": 0,
      "buy_count": 15,
      "sell_count": 0,
      "sector": "Internet"
    },
    {
      "name": "NAVER_2",
      "real_account_ref": "Account 8119599511",
      "allocation_ratio": 0.015,
      "strategy_type": "FOLLOWER",
      "rise_pct": 3.0,
      "dip_pct": 1.0,
      "total_value": 1500000,
      "cash": 1500000,
      "equity": 0,
      "unrealized_pnl": 0,
      "realized_pnl": 0,
      "buy_count": 0,
      "sell_count": 0,
      "sector": "Internet"
    },
    {
      "name": "NAVER_3",
      "real_account_ref": "Account 8119599511",
      "allocation_ratio": 0.015,
      "strategy_type": "FOLLOWER",
      "rise_pct": 3.0,
      "dip_pct": 2.0,
      "total_value": 1500000,
      "cash": 1500000,
      "equity": 0,
      "unrealized_pnl": 0,
      "realized_pnl": 0,
      "buy_count": 0,
      "sell_count": 0,
      "sector": "Internet"
    },
    {
      "name": "NAVER_4",
      "real_account_ref": "Account 8119599511",
      "allocation_ratio": 0.015,
      "strategy_type": "FOLLOWER",
      "rise_pct": 3.0,
      "dip_pct": 3.0,
      "total_value": 1500000,
      "cash": 1500000,
      "equity": 0,
      "unrealized_pnl": 0,
      "realized_pnl": 0,
      "buy_count": 0,
      "sell_count": 0,
      "sector": "Internet"
    },
    {
      "name": "NAVER_5",
      "real_account_ref": "Account 8119599511",
      "allocation_ratio": 0.015,
      "strategy_type": "FOLLOWER",
      "rise_pct": 3.0,
      "dip_pct": 4.0,
      "total_value": 1500000,
      "cash": 1500000,
      "equity": 0,
      "unrealized_pnl": 0,
      "realized_pnl": 0,
      "buy_count": 0,
      "sell_count": 0,
      "sector": "Internet"
    },
    {
      "name": "시프트업_1",
      "real_account_ref": "Account 8119599511",
      "allocation_ratio": 0.04000000000000001,
      "strategy_type": "LEADER",
      "rise_pct": 10.0,
      "dip_pct": 0,
      "total_value": 3912100,
      "cash": 796100,
      "equity": 3116000,
      "unrealized_pnl": -87900,
      "realized_pnl": 0,
      "buy_count": 21,
      "sell_count": 0,
      "sector": "Games"
    },
    {
      "name": "시프트업_2",
      "real_account_ref": "Account 8119599511",
      "allocation_ratio": 0.015,
      "strategy_type": "FOLLOWER",
      "rise_pct": 3.0,
      "dip_pct": 1.0,
      "total_value": 1472000,
      "cash": 127200,
      "equity": 1344800,
      "unrealized_pnl": -28000,
      "realized_pnl": 0,
      "buy_count": 21,
      "sell_count": 0,
      "sector": "Games"
    },
    {
      "name": "시프트업_3",
      "real_account_ref": "Account 8119599511",
      "allocation_ratio": 0.015,
      "strategy_type": "FOLLOWER",
      "rise_pct": 3.0,
      "dip_pct": 2.0,
      "total_value": 1496600,
      "cash": 1299800,
      "equity": 196800,
      "unrealized_pnl": -3400,
      "realized_pnl": 0,
      "buy_count": 3,
      "sell_count": 0,
      "sector": "Games"
    },
    {
      "name": "시프트업_4",
      "real_account_ref": "Account 8119599511",
      "allocation_ratio": 0.015,
      "strategy_type": "FOLLOWER",
      "rise_pct": 3.0,
      "dip_pct": 3.0,
      "total_value": 1500000,
      "cash": 1500000,
      "equity": 0,
      "unrealized_pnl": 0,
      "realized_pnl": 0,
      "buy_count": 0,
      "sell_count": 0,
      "sector": "Games"
    },
    {
      "name": "시프트업_5",
      "real_account_ref": "Account 8119599511",
      "allocation_ratio": 0.015,
      "strategy_type": "FOLLOWER",
      "rise_pct": 3.0,
      "dip_pct": 4.0,
      "total_value": 1500000,
      "cash": 1500000,
      "equity": 0,
      "unrealized_pnl": 0,
      "realized_pnl": 0,
      "buy_count": 0,
      "sell_count": 0,
      "sector": "Games"
    },
    {
      "name": "SK가스_1",
      "real_account_ref": "Account 8119599511",
      "allocation_ratio": 0.04000000000000001,
      "strategy_type": "LEADER",
      "rise_pct": 10.0,
      "dip_pct": 0,
      "total_value": 3878000,
      "cash": 368000,
      "equity": 3510000,
      "unrealized_pnl": -122000,
      "realized_pnl": 0,
      "buy_count": 15,
      "sell_count": 0,
      "sector": "Utilities"
    },
    {
      "name": "SK가스_2",
      "real_account_ref": "Account 8119599511",
      "allocation_ratio": 0.015,
      "strategy_type": "FOLLOWER",
      "rise_pct": 3.0,
      "dip_pct": 1.0,
      "total_value": 1448500,
      "cash": 44500,
      "equity": 1404000,
      "unrealized_pnl": -51500,
      "realized_pnl": 0,
      "buy_count": 6,
      "sell_count": 0,
      "sector": "Utilities"
    },
    {
      "name": "SK가스_3",
      "real_account_ref": "Account 8119599511",
      "allocation_ratio": 0.015,
      "strategy_type": "FOLLOWER",
      "rise_pct": 3.0,
      "dip_pct": 2.0,
      "total_value": 1468500,
      "cash": 64500,
      "equity": 1404000,
      "unrealized_pnl": -31500,
      "realized_pnl": 0,
      "buy_count": 6,
      "sell_count": 0,
      "sector": "Utilities"
    },
    {
      "name": "SK가스_4",
      "real_account_ref": "Account 8119599511",
      "allocation_ratio": 0.015,
      "strategy_type": "FOLLOWER",
      "rise_pct": 3.0,
      "dip_pct": 3.0,
      "total_value": 1479000,
      "cash": 75000,
      "equity": 1404000,
      "unrealized_pnl": -21000,
      "realized_pnl": 0,
      "buy_count": 6,
      "sell_count": 0,
      "sector": "Utilities"
    },
    {
      "name": "SK가스_5",
      "real_account_ref": "Account 8119599511",
      "allocation_ratio": 0.015,
      "strategy_type": "FOLLOWER",
      "rise_pct": 3.0,
      "dip_pct": 4.0,
      "total_value": 1500000,
      "cash": 1500000,
      "equity": 0,
      "unrealized_pnl": 0,
      "realized_pnl": 0,
      "buy_count": 0,
      "sell_count": 0,
      "sector": "Utilities"
    },
    {
      "name": "미스토홀딩스_1",
      "real_account_ref": "Account 8119599511",
      "allocation_ratio": 0.04000000000000001,
      "strategy_type": "LEADER",
      "rise_pct": 10.0,
      "dip_pct": 0,
      "total_value": 3809250,
      "cash": 652950,
      "equity": 3156300,
      "unrealized_pnl": -190750,
      "realized_pnl": 0,
      "buy_count": 21,
      "sell_count": 0,
      "sector": "Holdings"
    },
    {
      "name": "미스토홀딩스_2",
      "real_account_ref": "Account 8119599511",
      "allocation_ratio": 0.015,
      "strategy_type": "FOLLOWER",
      "rise_pct": 3.0,
      "dip_pct": 1.0,
      "total_value": 1443200,
      "cash": 40400,
      "equity": 1402800,
      "unrealized_pnl": -60100,
      "realized_pnl": 3300,
      "buy_count": 22,
      "sell_count": 1,
      "sector": "Holdings"
    },
    {
      "name": "미스토홀딩스_3",
      "real_account_ref": "Account 8119599511",
      "allocation_ratio": 0.015,
      "strategy_type": "FOLLOWER",
      "rise_pct": 3.0,
      "dip_pct": 2.0,
      "total_value": 1447500,
      "cash": 44700,
      "equity": 1402800,
      "unrealized_pnl": -52500,
      "realized_pnl": 0,
      "buy_count": 17,
      "sell_count": 0,
      "sector": "Holdings"
    },
    {
      "name": "미스토홀딩스_4",
      "real_account_ref": "Account 8119599511",
      "allocation_ratio": 0.015,
      "strategy_type": "FOLLOWER",
      "rise_pct": 3.0,
      "dip_pct": 3.0,
      "total_value": 1475500,
      "cash": 22600,
      "equity": 1452900,
      "unrealized_pnl": -24500,
      "realized_pnl": 0,
      "buy_count": 18,
      "sell_count": 0,
      "sector": "Holdings"
    },
    {
      "name": "미스토홀딩스_5",
      "real_account_ref": "Account 8119599511",
      "allocation_ratio": 0.015,
      "strategy_type": "FOLLOWER",
      "rise_pct": 3.0,
      "dip_pct": 4.0,
      "total_value": 1484900,
      "cash": 32000,
      "equity": 1452900,
      "unrealized_pnl": -15100,
      "realized_pnl": 0,
      "buy_count": 20,
      "sell_count": 0,
      "sector": "Holdings"
    },
    {
      "name": "LX홀딩스_1",
      "real_account_ref": "Account 8119599511",
      "allocation_ratio": 0.04000000000000001,
      "strategy_type": "LEADER",
      "rise_pct": 10.0,
      "dip_pct": 0,
      "total_value": 3871360,
      "cash": 752560,
      "equity": 3118800,
      "unrealized_pnl": -128640,
      "realized_pnl": 0,
      "buy_count": 21,
      "sell_count": 0,
      "sector": "Conglomerate"
    },
    {
      "name": "LX홀딩스_2",
      "real_account_ref": "Account 8119599511",
      "allocation_ratio": 0.015,
      "strategy_type": "FOLLOWER",
      "rise_pct": 3.0,
      "dip_pct": 1.0,
      "total_value": 1487110,
      "cash": 907510,
      "equity": 579600,
      "unrealized_pnl": -20410,
      "realized_pnl": 7520,
      "buy_count": 11,
      "sell_count": 3,
      "sector": "Conglomerate"
    },
    {
      "name": "LX홀딩스_3",
      "real_account_ref": "Account 8119599511",
      "allocation_ratio": 0.015,
      "strategy_type": "FOLLOWER",
      "rise_pct": 3.0,
      "dip_pct": 2.0,
      "total_value": 1489120,
      "cash": 1047520,
      "equity": 441600,
      "unrealized_pnl": -13360,
      "realized_pnl": 2480,
      "buy_count": 7,
      "sell_count": 1,
      "sector": "Conglomerate"
    },
    {
      "name": "LX홀딩스_4",
      "real_account_ref": "Account 8119599511",
      "allocation_ratio": 0.015,
      "strategy_type": "FOLLOWER",
      "rise_pct": 3.0,
      "dip_pct": 3.0,
      "total_value": 1494400,
      "cash": 1273600,
      "equity": 220800,
      "unrealized_pnl": -5600,
      "realized_pnl": 0,
      "buy_count": 3,
      "sell_count": 0,
      "sector": "Conglomerate"
    },
    {
      "name": "LX홀딩스_5",
      "real_account_ref": "Account 8119599511",
      "allocation_ratio": 0.015,
      "strategy_type": "FOLLOWER",
      "rise_pct": 3.0,
      "dip_pct": 4.0,
      "total_value": 1500000,
      "cash": 1500000,
      "equity": 0,
      "unrealized_pnl": 0,
      "realized_pnl": 0,
      "buy_count": 0,
      "sell_count": 0,
      "sector": "Conglomerate"
    },
    {
      "name": "한글과컴퓨터_1",
      "real_account_ref": "Account 8119599511",
      "allocation_ratio": 0.04000000000000001,
      "strategy_type": "LEADER",
      "rise_pct": 10.0,
      "dip_pct": 0,
      "total_value": 3891150,
      "cash": 727150,
      "equity": 3164000,
      "unrealized_pnl": -108850,
      "realized_pnl": 0,
      "buy_count": 21,
      "sell_count": 0,
      "sector": "Software"
    },
    {
      "name": "한글과컴퓨터_2",
      "real_account_ref": "Account 8119599511",
      "allocation_ratio": 0.015,
      "strategy_type": "FOLLOWER",
      "rise_pct": 3.0,
      "dip_pct": 1.0,
      "total_value": 1466950,
      "cash": 20550,
      "equity": 1446400,
      "unrealized_pnl": -33050,
      "realized_pnl": 0,
      "buy_count": 29,
      "sell_count": 0,
      "sector": "Software"
    },
    {
      "name": "한글과컴퓨터_3",
      "real_account_ref": "Account 8119599511",
      "allocation_ratio": 0.015,
      "strategy_type": "FOLLOWER",
      "rise_pct": 3.0,
      "dip_pct": 2.0,
      "total_value": 1472825,
      "cash": 3825,
      "equity": 1469000,
      "unrealized_pnl": -27175,
      "realized_pnl": 0,
      "buy_count": 20,
      "sell_count": 0,
      "sector": "Software"
    },
    {
      "name": "한글과컴퓨터_4",
      "real_account_ref": "Account 8119599511",
      "allocation_ratio": 0.015,
      "strategy_type": "FOLLOWER",
      "rise_pct": 3.0,
      "dip_pct": 3.0,
      "total_value": 1491275,
      "cash": 587275,
      "equity": 904000,
      "unrealized_pnl": -10209.302325581433,
      "realized_pnl": 1484,
      "buy_count": 13,
      "sell_count": 1,
      "sector": "Software"
    },
    {
      "name": "한글과컴퓨터_5",
      "real_account_ref": "Account 8119599511",
      "allocation_ratio": 0.015,
      "strategy_type": "FOLLOWER",
      "rise_pct": 3.0,
      "dip_pct": 4.0,
      "total_value": 1500200,
      "cash": 822200,
      "equity": 678000,
      "unrealized_pnl": -1525.0,
      "realized_pnl": 1725,
      "buy_count": 10,
      "sell_count": 1,
      "sector": "Software"
    },
    {
      "name": "SOOP_1",
      "real_account_ref": "Account 8119599511",
      "allocation_ratio": 0.04000000000000001,
      "strategy_type": "LEADER",
      "rise_pct": 10.0,
      "dip_pct": 0,
      "total_value": 3947600,
      "cash": 667000,
      "equity": 3280600,
      "unrealized_pnl": -52400,
      "realized_pnl": 0,
      "buy_count": 21,
      "sell_count": 0,
      "sector": "Internet"
    },
    {
      "name": "SOOP_2",
      "real_account_ref": "Account 8119599511",
      "allocation_ratio": 0.015,
      "strategy_type": "FOLLOWER",
      "rise_pct": 3.0,
      "dip_pct": 1.0,
      "total_value": 1521500,
      "cash": 544300,
      "equity": 977200,
      "unrealized_pnl": 920.0,
      "realized_pnl": 20580,
      "buy_count": 20,
      "sell_count": 5,
      "sector": "Internet"
    },
    {
      "name": "SOOP_3",
      "real_account_ref": "Account 8119599511",
      "allocation_ratio": 0.015,
      "strategy_type": "FOLLOWER",
      "rise_pct": 3.0,
      "dip_pct": 2.0,
      "total_value": 1510400,
      "cash": 1021800,
      "equity": 488600,
      "unrealized_pnl": 328.57142857136205,
      "realized_pnl": 10071,
      "buy_count": 12,
      "sell_count": 5,
      "sector": "Internet"
    },
    {
      "name": "SOOP_4",
      "real_account_ref": "Account 8119599511",
      "allocation_ratio": 0.015,
      "strategy_type": "FOLLOWER",
      "rise_pct": 3.0,
      "dip_pct": 3.0,
      "total_value": 1505100,
      "cash": 1365500,
      "equity": 139600,
      "unrealized_pnl": -1500,
      "realized_pnl": 6600,
      "buy_count": 4,
      "sell_count": 2,
      "sector": "Internet"
    },
    {
      "name": "SOOP_5",
      "real_account_ref": "Account 8119599511",
      "allocation_ratio": 0.015,
      "strategy_type": "FOLLOWER",
      "rise_pct": 3.0,
      "dip_pct": 4.0,
      "total_value": 1504400,
      "cash": 1364800,
      "equity": 139600,
      "unrealized_pnl": 0,
      "realized_pnl": 4400,
      "buy_count": 4,
      "sell_count": 2,
      "sector": "Internet"
    },
    {
      "name": "휴메딕스_1",
      "real_account_ref": "Account 8119599511",
      "allocation_ratio": 0.04000000000000001,
      "strategy_type": "LEADER",
      "rise_pct": 10.0,
      "dip_pct": 0,
      "total_value": 3867600,
      "cash": 517500,
      "equity": 3350100,
      "unrealized_pnl": -132400,
      "realized_pnl": 0,
      "buy_count": 21,
      "sell_count": 0,
      "sector": "Pharma"
    },
    {
      "name": "휴메딕스_2",
      "real_account_ref": "Account 8119599511",
      "allocation_ratio": 0.015,
      "strategy_type": "FOLLOWER",
      "rise_pct": 3.0,
      "dip_pct": 1.0,
      "total_value": 1468650,
      "cash": 566700,
      "equity": 901950,
      "unrealized_pnl": -40900,
      "realized_pnl": 9550,
      "buy_count": 16,
      "sell_count": 1,
      "sector": "Pharma"
    },
    {
      "name": "휴메딕스_3",
      "real_account_ref": "Account 8119599511",
      "allocation_ratio": 0.015,
      "strategy_type": "FOLLOWER",
      "rise_pct": 3.0,
      "dip_pct": 2.0,
      "total_value": 1474350,
      "cash": 572400,
      "equity": 901950,
      "unrealized_pnl": -32700,
      "realized_pnl": 7050,
      "buy_count": 15,
      "sell_count": 1,
      "sector": "Pharma"
    },
    {
      "name": "휴메딕스_4",
      "real_account_ref": "Account 8119599511",
      "allocation_ratio": 0.015,
      "strategy_type": "FOLLOWER",
      "rise_pct": 3.0,
      "dip_pct": 3.0,
      "total_value": 1490900,
      "cash": 889600,
      "equity": 601300,
      "unrealized_pnl": -16200,
      "realized_pnl": 7100,
      "buy_count": 12,
      "sell_count": 1,
      "sector": "Pharma"
    },
    {
      "name": "휴메딕스_5",
      "real_account_ref": "Account 8119599511",
      "allocation_ratio": 0.015,
      "strategy_type": "FOLLOWER",
      "rise_pct": 3.0,
      "dip_pct": 4.0,
      "total_value": 1500000,
      "cash": 1027550,
      "equity": 472450,
      "unrealized_pnl": -8700,
      "realized_pnl": 8700,
      "buy_count": 10,
      "sell_count": 1,
      "sector": "Pharma"
    },
    {
      "name": "삼양컴텍_1",
      "real_account_ref": "Account 8119599511",
      "allocation_ratio": 0.04000000000000001,
      "strategy_type": "LEADER",
      "rise_pct": 10.0,
      "dip_pct": 0,
      "total_value": 4146610,
      "cash": 735340,
      "equity": 3411270,
      "unrealized_pnl": 146610,
      "realized_pnl": 0,
      "buy_count": 21,
      "sell_count": 0,
      "sector": "Defense"
    },
    {
      "name": "삼양컴텍_2",
      "real_account_ref": "Account 8119599511",
      "allocation_ratio": 0.015,
      "strategy_type": "FOLLOWER",
      "rise_pct": 3.0,
      "dip_pct": 1.0,
      "total_value": 1593290,
      "cash": 1593290,
      "equity": 0,
      "unrealized_pnl": 0,
      "realized_pnl": 93290,
      "buy_count": 17,
      "sell_count": 6,
      "sector": "Defense"
    },
    {
      "name": "삼양컴텍_3",
      "real_account_ref": "Account 8119599511",
      "allocation_ratio": 0.015,
      "strategy_type": "FOLLOWER",
      "rise_pct": 3.0,
      "dip_pct": 2.0,
      "total_value": 1587720,
      "cash": 1587720,
      "equity": 0,
      "unrealized_pnl": 0,
      "realized_pnl": 87720,
      "buy_count": 15,
      "sell_count": 1,
      "sector": "Defense"
    },
    {
      "name": "삼양컴텍_4",
      "real_account_ref": "Account 8119599511",
      "allocation_ratio": 0.015,
      "strategy_type": "FOLLOWER",
      "rise_pct": 3.0,
      "dip_pct": 3.0,
      "total_value": 1562150,
      "cash": 1562150,
      "equity": 0,
      "unrealized_pnl": 0,
      "realized_pnl": 62150,
      "buy_count": 10,
      "sell_count": 1,
      "sector": "Defense"
    },
    {
      "name": "삼양컴텍_5",
      "real_account_ref": "Account 8119599511",
      "allocation_ratio": 0.015,
      "strategy_type": "FOLLOWER",
      "rise_pct": 3.0,
      "dip_pct": 4.0,
      "total_value": 1512780,
      "cash": 1512780,
      "equity": 0,
      "unrealized_pnl": 0,
      "realized_pnl": 12780,
      "buy_count": 2,
      "sell_count": 1,
      "sector": "Defense"
    },
    {
      "name": "한국앤컴퍼니_1",
      "real_account_ref": "Account 8119599511",
      "allocation_ratio": 0.04000000000000001,
      "strategy_type": "LEADER",
      "rise_pct": 10.0,
      "dip_pct": 0,
      "total_value": 3755400,
      "cash": 552600,
      "equity": 3202800,
      "unrealized_pnl": -244600,
      "realized_pnl": 0,
      "buy_count": 21,
      "sell_count": 0,
      "sector": "Automotive"
    },
    {
      "name": "한국앤컴퍼니_2",
      "real_account_ref": "Account 8119599511",
      "allocation_ratio": 0.015,
      "strategy_type": "FOLLOWER",
      "rise_pct": 3.0,
      "dip_pct": 1.0,
      "total_value": 1446100,
      "cash": 347100,
      "equity": 1099000,
      "unrealized_pnl": -55123.33333333349,
      "realized_pnl": 1223,
      "buy_count": 17,
      "sell_count": 1,
      "sector": "Automotive"
    },
    {
      "name": "한국앤컴퍼니_3",
      "real_account_ref": "Account 8119599511",
      "allocation_ratio": 0.015,
      "strategy_type": "FOLLOWER",
      "rise_pct": 3.0,
      "dip_pct": 2.0,
      "total_value": 1463600,
      "cash": 741400,
      "equity": 722200,
      "unrealized_pnl": -37552.17391304346,
      "realized_pnl": 1152,
      "buy_count": 12,
      "sell_count": 1,
      "sector": "Automotive"
    },
    {
      "name": "한국앤컴퍼니_4",
      "real_account_ref": "Account 8119599511",
      "allocation_ratio": 0.015,
      "strategy_type": "FOLLOWER",
      "rise_pct": 3.0,
      "dip_pct": 3.0,
      "total_value": 1459900,
      "cash": 737700,
      "equity": 722200,
      "unrealized_pnl": -40100,
      "realized_pnl": 0,
      "buy_count": 10,
      "sell_count": 0,
      "sector": "Automotive"
    },
    {
      "name": "한국앤컴퍼니_5",
      "real_account_ref": "Account 8119599511",
      "allocation_ratio": 0.015,
      "strategy_type": "FOLLOWER",
      "rise_pct": 3.0,
      "dip_pct": 4.0,
      "total_value": 1469000,
      "cash": 872400,
      "equity": 596600,
      "unrealized_pnl": -32015.78947368427,
      "realized_pnl": 1015,
      "buy_count": 10,
      "sell_count": 1,
      "sector": "Automotive"
    },
    {
      "name": "동아쏘시오홀딩스_1",
      "real_account_ref": "Account 8119599511",
      "allocation_ratio": 0.04000000000000001,
      "strategy_type": "LEADER",
      "rise_pct": 10.0,
      "dip_pct": 0,
      "total_value": 3923500,
      "cash": 312000,
      "equity": 3611500,
      "unrealized_pnl": -76500,
      "realized_pnl": 0,
      "buy_count": 21,
      "sell_count": 0,
      "sector": "Pharma"
    },
    {
      "name": "동아쏘시오홀딩스_2",
      "real_account_ref": "Account 8119599511",
      "allocation_ratio": 0.015,
      "strategy_type": "FOLLOWER",
      "rise_pct": 3.0,
      "dip_pct": 1.0,
      "total_value": 1485500,
      "cash": 903000,
      "equity": 582500,
      "unrealized_pnl": -14500,
      "realized_pnl": 0,
      "buy_count": 5,
      "sell_count": 0,
      "sector": "Pharma"
    },
    {
      "name": "동아쏘시오홀딩스_3",
      "real_account_ref": "Account 8119599511",
      "allocation_ratio": 0.015,
      "strategy_type": "FOLLOWER",
      "rise_pct": 3.0,
      "dip_pct": 2.0,
      "total_value": 1494200,
      "cash": 1028200,
      "equity": 466000,
      "unrealized_pnl": -5800,
      "realized_pnl": 0,
      "buy_count": 4,
      "sell_count": 0,
      "sector": "Pharma"
    },
    {
      "name": "동아쏘시오홀딩스_4",
      "real_account_ref": "Account 8119599511",
      "allocation_ratio": 0.015,
      "strategy_type": "FOLLOWER",
      "rise_pct": 3.0,
      "dip_pct": 3.0,
      "total_value": 1499000,
      "cash": 1382500,
      "equity": 116500,
      "unrealized_pnl": -1000,
      "realized_pnl": 0,
      "buy_count": 1,
      "sell_count": 0,
      "sector": "Pharma"
    },
    {
      "name": "동아쏘시오홀딩스_5",
      "real_account_ref": "Account 8119599511",
      "allocation_ratio": 0.015,
      "strategy_type": "FOLLOWER",
      "rise_pct": 3.0,
      "dip_pct": 4.0,
      "total_value": 1500000,
      "cash": 1500000,
      "equity": 0,
      "unrealized_pnl": 0,
      "realized_pnl": 0,
      "buy_count": 0,
      "sell_count": 0,
      "sector": "Pharma"
    }
  ]
}